CHANGES.rst
LICENSE
MANIFEST.in
README.rst
erppeek.ini
erppeek.py
setup.cfg
setup.py
docs/Makefile
docs/api.rst
docs/conf.py
docs/developer.rst
docs/index.rst
docs/intro.rst
docs/make.bat
docs/tutorial.rst
medad_odoo.egg-info/PKG-INFO
medad_odoo.egg-info/SOURCES.txt
medad_odoo.egg-info/dependency_links.txt
medad_odoo.egg-info/entry_points.txt
medad_odoo.egg-info/not-zip-safe
medad_odoo.egg-info/top_level.txt
tests/__init__.py
tests/_common.py
tests/test_client.py
tests/test_interact.py
tests/test_model.py
tests/test_util.py